grnasearch/__init__.py
grnasearch/gRNA.py
gRNAsearch-0.0.3.dist-info/LICENSE
gRNAsearch-0.0.3.dist-info/METADATA
gRNAsearch-0.0.3.dist-info/WHEEL
gRNAsearch-0.0.3.dist-info/top_level.txt
gRNAsearch-0.0.3.dist-info/RECORD
