Metadata-Version: 2.1
Name: gRNAsearch
Version: 0.0.3
Summary: Search for guide RNA sites in PCR tags
Home-page: https://github.com/rhong3/gRNAsearch
Author: Runyu Hong
Author-email: Runyu.Hong@nyu.edu
License: UNKNOWN
Platform: UNKNOWN
Classifier: Programming Language :: Python :: 3.6
Classifier: License :: OSI Approved :: MIT License
Requires-Dist: biopython (>=1.76)
Requires-Dist: numpy (>=1.17.5)
Requires-Dist: pandas (>=0.23)
